MANIFEST.in
README.md
setup.py
deleuze/__init__.py
deleuze/tool.py
deleuze.egg-info/PKG-INFO
deleuze.egg-info/SOURCES.txt
deleuze.egg-info/dependency_links.txt
deleuze.egg-info/entry_points.txt
deleuze.egg-info/requires.txt
deleuze.egg-info/top_level.txt
deleuze/project-skeleton/README.md
deleuze/project-skeleton/requirements.txt
deleuze/project-skeleton/setup.jinja.py
deleuze/project-skeleton/NAME/__init__.py
deleuze/project-skeleton/bin/NAME.py
deleuze/project-skeleton/reqs/common.txt
deleuze/project-skeleton/reqs/dev.txt
deleuze/project-skeleton/reqs/production.txt
deleuze/project-skeleton/reqs/test.txt
deleuze/project-skeleton/tests/__init__.py
deleuze/project-skeleton/tests/base.py
deleuze/project-skeleton/tests/factories.py
deleuze/project-skeleton/tests/test_NAME.py