Metadata-Version: 1.1
Name: deleuze
Version: 0.9
Summary: Simple python project creation tool - inspired by Leiningen.
Home-page: https://github.com/etscrivner/deleuze
Author: Eric Scrivner
Author-email: eric.t.scrivner@gmail.com
License: BSD
Download-URL: https://github.com/etscrivner/deleuze
Keywords: project,project creation,scaffolding,scaffold
Platform: UNKNOWN
